knit_space/__init__.py
knit_space/marker.py
knit_space/models.py
knit_space/obscurers/bijective_char_mapper.py
knit_space/obscurers/char_obfuscator.py
knit_space/tests/__init__.py
knit_space/tests/base.py
knit_space/tests/basic_math_tests.py
knit_space/tests/cardinality_test.py
knit_space/tests/chess_memory_tests.py
knit_space/tests/coding_problem_defs.py
knit_space/tests/coding_tests.py
knit_space/tests/decimal_test.py
knit_space/tests/false_assertion_math_tests.py
knit_space/tests/long_context_tests.py
knit_space/tests/medmcqa_obfuscated_choice_tests.py
knit_space/tests/mmlu_obfuscated_choice_tests.py
knit_space/tests/mmlu_obfuscated_tests.py
knit_space/tests/needle_in_a_haystack.py
knit_space/tests/real_time_tests.py
knit_space/tests/rule_tests.py
knit_space/tests/rule_tests_fake_guide.py
knit_space/tests/sentence_obs_tests.py
knit_space/tests/sudoku_test.py
knit_space/utils/code_executor.py
ks_llm_ranker-0.1.6.dist-info/licenses/LICENSE
ks_llm_ranker-0.1.6.dist-info/METADATA
ks_llm_ranker-0.1.6.dist-info/WHEEL
ks_llm_ranker-0.1.6.dist-info/top_level.txt
ks_llm_ranker-0.1.6.dist-info/RECORD
