Metadata-Version: 2.4
Name: ks-llm-ranker
Version: 0.1.6
Summary: A Python library for knit_space operations.
Author: Chinmay Sultanpuri
License: MIT License
Project-URL: Homepage, https://github.com/C-you-know/Action-Based-LLM-Testing-Harness
Classifier: Programming Language :: Python :: 3
Classifier: License :: OSI Approved :: MIT License
Classifier: Operating System :: OS Independent
Requires-Python: <3.13,>=3.8
License-File: LICENSE
Requires-Dist: beautifulsoup4==4.13.3
Requires-Dist: cerebras-cloud-sdk==1.35.0
Requires-Dist: chess==1.11.2
Requires-Dist: cohere==5.14.0
Requires-Dist: datasets==3.6.0
Requires-Dist: Flask==3.1.1
Requires-Dist: google-generativeai==0.8.5
Requires-Dist: groq==0.25.0
Requires-Dist: mistralai==1.7.1
Requires-Dist: mpmath==1.3.0
Requires-Dist: numpy>=1.23
Requires-Dist: openai==1.69.0
Requires-Dist: Pillow==11.1.0
Requires-Dist: requests==2.32.3
Requires-Dist: together==1.4.6
Requires-Dist: torch==2.7.0
Requires-Dist: transformers==4.51.3
Requires-Dist: yfinance==0.2.61
Dynamic: license-file
